[{"id":"24","title":"Rise og Sivagami","imageUrl":"https://encrypted-tbn0.gstatic.com/images?q=tbn%3AANd9GcSZzJ5eC3zoZhp9ov1AUiNN4pBIaLomN9kehklRHw6b5usZEQ3H","description":"Fantastic story told in an amazing way. Throughout the reading we will feel all the emotions of Sivagami. One of the best books I have read. ...","price":"130"},{"title":"ROle of the Dice","imageUrl":"https://encrypted-tbn0.gstatic.com/images?q=tbn%3AANd9GcR2HuuoOGxG0LqHcrjguwEKCfTqaomzjRw3AkFz3r2qGGUc278u","description":"Right from calling Duryodhana as Suyodhana and Dusshasana becoming Sushasana a clever change from ‘dur’ (negative) to ‘su’ (positive) to giving a voice to the unsung heroes of the greatest epic from India Anand Neelakantan has aptly made all his readers see the other side of the story in his book ‘Ajaya – Epic of the Kaurava Clan’.","price":"20","id":"17.591105561277764"}]